pysimplicialcubature/__init__.py
pysimplicialcubature/simplicialcubature.py
pysimplicialcubature-0.2.0.dist-info/LICENSE
pysimplicialcubature-0.2.0.dist-info/METADATA
pysimplicialcubature-0.2.0.dist-info/WHEEL
pysimplicialcubature-0.2.0.dist-info/RECORD
