Metadata-Version: 2.1
Name: pysimplicialcubature
Version: 0.2.0
Summary: Integration on simplices.
Home-page: https://github.com/stla/PySimplicialCubature
License: GPL-3.0-only
Keywords: integration,simplex
Author: Stéphane Laurent
Author-email: laurent_step@outlook.fr
Requires-Python: >=3.9,<4.0
Classifier: License :: OSI Approved :: GNU General Public License v3 (GPLv3)
Classifier: Programming Language :: Python :: 3
Classifier: Programming Language :: Python :: 3.9
Classifier: Programming Language :: Python :: 3.10
Classifier: Programming Language :: Python :: 3.11
Classifier: Programming Language :: Python :: 3.12
Provides-Extra: docs
Requires-Dist: numpy (>=1.23.5,<2.0.0)
Requires-Dist: sphinx (>=5.3.0,<6.0.0) ; extra == "docs"
Requires-Dist: sphinx-rtd-theme (>=1.1.1,<2.0.0) ; extra == "docs"
Requires-Dist: sphinxcontrib-napoleon (>=0.7,<0.8) ; extra == "docs"
Requires-Dist: sphinxcontrib-restbuilder (>=0.3,<0.4) ; extra == "docs"
Requires-Dist: sympy (>=1.11.1,<2.0.0)
Project-URL: Documentation, https://pysimplicialcubature.readthedocs.io/en/latest/
